rusty_whipsnake/__init__.py
rusty_whipsnake/examples/__init__.py
rusty_whipsnake/examples/option.py
rusty_whipsnake/examples/result.py
rusty_whipsnake/option.py
rusty_whipsnake/py.typed
rusty_whipsnake/result.py
rusty_whipsnake-0.1.0.dist-info/LICENSE
rusty_whipsnake-0.1.0.dist-info/METADATA
rusty_whipsnake-0.1.0.dist-info/WHEEL
rusty_whipsnake-0.1.0.dist-info/RECORD
